{
	"modules":[
	
	{
		"module":"Welcome",
		"url":"screens/welcome.html",
		"id":0,
		"topics":[
		],
		"audio": false,
		"overlay": true,
		"video_url": "videos/video1_1080px.mp4"
	},
	
	{
		"module":"Learning Objectives",
		"url":"screens/intro.html",
		"id":1,
		"topics":[
		],
		"audio": false,
		"overlay": true,
		"video_url": "videos/video1_1080px.mp4"
	},
	{
		"module":"Pre-test",
		"url":"screens/pretest.html",
		"id":2,
		"topics":[
		],
		"audio": true,
		"audio_url": "audio/Narrator.mp3",
		"overlay": false,
		"video_url": "videos/video1_1080px.mp4"
	},
		{
		"module":"Importance of Fire Safety of the health",
		"url":"screens/acronyms.html",
		"id":3,
		"topics":[
		],
		"audio": false,
		"overlay": true,
		"video_url": "videos/video1_1080px.mp4"
	},
	
	{
		"module":"Causes of Fire",
		"url":"screens/references.html",
		"id":4,
		"topics":[
		],
		"audio": true,
		"audio_url": "audio/FireSafety2.mp3",
		"overlay": false,
		"video_url": "videos/video1_1080px.mp4"
	},
	{
		"module":"Fire Tetrahedron",
		"url":"screens/references1.html",
		"id":5,
		"topics":[
		],
		"audio": false,
		"overlay": false,
		"video_url": "videos/video1_1080px.mp4"
	},
	{
		"module":"Types of Fire",
		"url":"screens/references2.html",
		"id":6,
		"topics":[
		],
		"audio": false,
		"overlay": false,
		"video_url": "videos/video1_1080px.mp4"
	},
	
	{
		"module":"Post-test",
		"url":"screens/postTest.html",
		"id":10,
		"topics":[
		],
		"audio": false,
		"overlay": false,
		"video_url": "videos/video1_1080px.mp4"
	}
   ]
}